nonebot_plugin_ddrace/__init__.py
nonebot_plugin_ddrace/_version.py
nonebot_plugin_ddrace/commands/__init__.py
nonebot_plugin_ddrace/commands/bind.py
nonebot_plugin_ddrace/commands/player.py
nonebot_plugin_ddrace/config.py
nonebot_plugin_ddrace/models/__init__.py
nonebot_plugin_ddrace/models/data.py
nonebot_plugin_ddrace/models/ddr_get_data.py
nonebot_plugin_ddrace/models/network.py
nonebot_plugin_ddrace/models/pic_generade.py
nonebot_plugin_ddrace/static/css-halloween.css
nonebot_plugin_ddrace/static/css.css
nonebot_plugin_ddrace/static/map_global_ranks.css
nonebot_plugin_ddrace/static/player_global_ranks.css
nonebot_plugin_ddrace/utils/__init__.py
nonebot_plugin_ddrace/utils/cache.py
nonebot_plugin_ddrace/utils/constants.py
nonebot_plugin_ddrace/utils/tools.py
nonebot_plugin_ddrace/utils/triggers.py
nonebot_plugin_ddrace-0.0.6.dist-info/LICENSE
nonebot_plugin_ddrace-0.0.6.dist-info/METADATA
nonebot_plugin_ddrace-0.0.6.dist-info/WHEEL
nonebot_plugin_ddrace-0.0.6.dist-info/RECORD
