Metadata-Version: 2.1
Name: nonebot-plugin-ddrace
Version: 0.0.6
Summary: 提供 DDNet 成绩查询功能
Home-page: https://github.com/gongfuture/nonebot-plugin-ddrace
License: MIT
Keywords: bot,qq,qqbot,onebotv11,onebot,nonebot2,nonebot,ddrace,ddnet
Author: gongfuture
Author-email: gongfuture@outlook.com
Requires-Python: >3.9,<4.0
Classifier: License :: OSI Approved :: MIT License
Classifier: Programming Language :: Python :: 3
Classifier: Programming Language :: Python :: 3.10
Classifier: Programming Language :: Python :: 3.11
Classifier: Programming Language :: Python :: 3.12
Classifier: Programming Language :: Python :: 3.13
Requires-Dist: beautifulsoup4 (>=4.12.3,<5.0.0)
Requires-Dist: httpx (>=0.24.1,<0.27.2)
Requires-Dist: nonebot-adapter-onebot (>=2.4.5,<3.0.0)
Requires-Dist: nonebot-plugin-htmlrender (>=0.3.5)
Requires-Dist: nonebot-plugin-localstore (>=0.7.0)
Requires-Dist: nonebot-plugin-send-anything-anywhere (>=0.5,<0.8)
Requires-Dist: nonebot-plugin-userinfo (>=0.2.0)
Requires-Dist: nonebot2 (>=2.3.3)
Requires-Dist: nonebot_plugin_apscheduler (>=0.2.0)
Requires-Dist: pydantic (<3.0.0)
Project-URL: Bug Tracker, https://github.com/gongfuture/nonebot-plugin-ddrace/issues
Project-URL: Repository, https://github.com/gongfuture/nonebot-plugin-ddrace
